{
  "updated": "2026-07-17",
  "stocks": {
    "ABBOTINDIA": {
      "ltp": 28055,
      "change": 185,
      "changePct": 0.66
    },
    "ADANIGREEN": {
      "ltp": 1513.9,
      "change": -29.8,
      "changePct": -1.93
    },
    "ADANIPOWER": {
      "ltp": 214.45,
      "change": -2.12,
      "changePct": -0.98
    },
    "ALKEM": {
      "ltp": 5563,
      "change": -146,
      "changePct": -2.56
    },
    "ASHOKLEY": {
      "ltp": 155.23,
      "change": 0.36,
      "changePct": 0.23
    },
    "AUROPHARMA": {
      "ltp": 1533.4,
      "change": -15,
      "changePct": -0.97
    },
    "AXISBANK": {
      "ltp": 1328.5,
      "change": 20.9,
      "changePct": 1.6
    },
    "BANKBARODA": {
      "ltp": 246.8,
      "change": -1.5,
      "changePct": -0.6
    },
    "BOSCHLTD": {
      "ltp": 40855,
      "change": -255,
      "changePct": -0.62
    },
    "BPCL": {
      "ltp": 315.55,
      "change": 3.55,
      "changePct": 1.14
    },
    "BRITANNIA": {
      "ltp": 5412.5,
      "change": 102,
      "changePct": 1.92
    },
    "CANBK": {
      "ltp": 125.01,
      "change": -0.89,
      "changePct": -0.71
    },
    "CIPLA": {
      "ltp": 1418.7,
      "change": -10.8,
      "changePct": -0.76
    },
    "COALINDIA": {
      "ltp": 427.65,
      "change": 0.3,
      "changePct": 0.07
    },
    "COFORGE": {
      "ltp": 1508.4,
      "change": -22.3,
      "changePct": -1.46
    },
    "COLPAL": {
      "ltp": 2042.4,
      "change": 41.3,
      "changePct": 2.06
    },
    "DABUR": {
      "ltp": 427.2,
      "change": -2.25,
      "changePct": -0.52
    },
    "DIVISLAB": {
      "ltp": 7247.5,
      "change": -68.5,
      "changePct": -0.94
    },
    "DRREDDY": {
      "ltp": 1211.2,
      "change": -13.2,
      "changePct": -1.08
    },
    "EICHERMOT": {
      "ltp": 7563.5,
      "change": 145,
      "changePct": 1.95
    },
    "EMAMILTD": {
      "ltp": 409.45,
      "change": 2.5,
      "changePct": 0.61
    },
    "FEDERALBNK": {
      "ltp": 349,
      "change": 22.4,
      "changePct": 6.86
    },
    "GODREJCP": {
      "ltp": 1071.9,
      "change": 14.2,
      "changePct": 1.34
    },
    "HCLTECH": {
      "ltp": 1203.9,
      "change": 16.5,
      "changePct": 1.39
    },
    "HDFCBANK": {
      "ltp": 819.6,
      "change": 11.3,
      "changePct": 1.4
    },
    "HEROMOTOCO": {
      "ltp": 4909.9,
      "change": 11.9,
      "changePct": 0.24
    },
    "HINDUNILVR": {
      "ltp": 2143.8,
      "change": 45.4,
      "changePct": 2.16
    },
    "HYUNDAI": {
      "ltp": 1993.3,
      "change": -31.7,
      "changePct": -1.57
    },
    "ICICIBANK": {
      "ltp": 1444.3,
      "change": 26.1,
      "changePct": 1.84
    },
    "INDUSINDBK": {
      "ltp": 1027.2,
      "change": 13.7,
      "changePct": 1.35
    },
    "INFY": {
      "ltp": 1096.5,
      "change": 14.1,
      "changePct": 1.3
    },
    "IOC": {
      "ltp": 141.69,
      "change": -0.11,
      "changePct": -0.08
    },
    "IPCALAB": {
      "ltp": 1900.6,
      "change": 10.4,
      "changePct": 0.55
    },
    "ITC": {
      "ltp": 280.7,
      "change": 1.35,
      "changePct": 0.48
    },
    "KOTAKBANK": {
      "ltp": 389.95,
      "change": 12.8,
      "changePct": 3.39
    },
    "LUPIN": {
      "ltp": 2443.2,
      "change": -57.3,
      "changePct": -2.29
    },
    "MARICO": {
      "ltp": 844,
      "change": 4.65,
      "changePct": 0.55
    },
    "MARUTI": {
      "ltp": 13803,
      "change": 20,
      "changePct": 0.15
    },
    "MPHASIS": {
      "ltp": 2394.2,
      "change": 42.2,
      "changePct": 1.79
    },
    "NESTLEIND": {
      "ltp": 1427.2,
      "change": 3.7,
      "changePct": 0.26
    },
    "NTPC": {
      "ltp": 341.85,
      "change": -0.6,
      "changePct": -0.18
    },
    "ONGC": {
      "ltp": 247.29,
      "change": 0.54,
      "changePct": 0.22
    },
    "PERSISTENT": {
      "ltp": 5183.9,
      "change": 124.6,
      "changePct": 2.46
    },
    "PNB": {
      "ltp": 105.77,
      "change": 0.55,
      "changePct": 0.52
    },
    "POWERGRID": {
      "ltp": 283.55,
      "change": 2.8,
      "changePct": 1
    },
    "RELIANCE": {
      "ltp": 1327.2,
      "change": 30.6,
      "changePct": 2.36
    },
    "SBIN": {
      "ltp": 1044.3,
      "change": 13.1,
      "changePct": 1.27
    },
    "SUNPHARMA": {
      "ltp": 1932.6,
      "change": -17.5,
      "changePct": -0.9
    },
    "TATACONSUM": {
      "ltp": 1088.6,
      "change": 0.1,
      "changePct": 0.01
    },
    "TATAPOWER": {
      "ltp": 377.25,
      "change": 0.15,
      "changePct": 0.04
    },
    "TCS": {
      "ltp": 2269,
      "change": 68,
      "changePct": 3.09
    },
    "TECHM": {
      "ltp": 1572.9,
      "change": 62.6,
      "changePct": 4.14
    },
    "TORNTPHARM": {
      "ltp": 4763,
      "change": -224.6,
      "changePct": -4.5
    },
    "TVSMOTOR": {
      "ltp": 3618.2,
      "change": 54.7,
      "changePct": 1.54
    },
    "WIPRO": {
      "ltp": 176,
      "change": -1.74,
      "changePct": -0.98
    },
    "BAJAJ-AUTO": {
      "ltp": 10443,
      "change": 111.5,
      "changePct": 1.08
    },
    "M&M": {
      "ltp": 3179.2,
      "change": 61.4,
      "changePct": 1.97
    }
  }
}